odoo/addons/stock_move_line_serial_unique/README.rst
odoo/addons/stock_move_line_serial_unique/__init__.py
odoo/addons/stock_move_line_serial_unique/__manifest__.py
odoo/addons/stock_move_line_serial_unique/i18n/it.po
odoo/addons/stock_move_line_serial_unique/i18n/stock_move_line_serial_unique.pot
odoo/addons/stock_move_line_serial_unique/models/__init__.py
odoo/addons/stock_move_line_serial_unique/models/stock_move_line.py
odoo/addons/stock_move_line_serial_unique/readme/CONTRIBUTORS.rst
odoo/addons/stock_move_line_serial_unique/readme/DESCRIPTION.rst
odoo/addons/stock_move_line_serial_unique/static/description/icon.png
odoo/addons/stock_move_line_serial_unique/static/description/index.html
odoo/addons/stock_move_line_serial_unique/tests/__init__.py
odoo/addons/stock_move_line_serial_unique/tests/test_stock_move_line_serial_unique.py
odoo_addon_stock_move_line_serial_unique-16.0.1.0.0.5.dist-info/METADATA
odoo_addon_stock_move_line_serial_unique-16.0.1.0.0.5.dist-info/WHEEL
odoo_addon_stock_move_line_serial_unique-16.0.1.0.0.5.dist-info/top_level.txt
odoo_addon_stock_move_line_serial_unique-16.0.1.0.0.5.dist-info/RECORD
